sopy/__init__.py
sopy/run.py
sopy/sopy.py
sopy-1.6.dist-info/METADATA
sopy-1.6.dist-info/WHEEL
sopy-1.6.dist-info/top_level.txt
sopy-1.6.dist-info/RECORD
