Metadata-Version: 2.1
Name: sopy
Version: 1.6
Summary: A neat way to write SOPs using python
Home-page: https://github.com/AakashSasikumar/SOPy
Author: Aakash Sasikumar and Sourav Johar
Author-email: aakash.sasikumar@protonmail.com
License: MIT
Platform: UNKNOWN
Requires-Dist: jinja2
Requires-Dist: beautifulsoup4
Requires-Dist: requests
